{
  "schemaVersion": 1,
  "events": [
    {
      "generatedAt": "2026-02-23T06:55:00.613Z",
      "addedCount": 0,
      "changedCount": 1,
      "removedCount": 0,
      "totalFiles": 518,
      "added": [],
      "changed": [
        "/pinball/data/pinball_library_v2.json"
      ],
      "removed": []
    },
    {
      "generatedAt": "2026-02-23T06:53:59.140Z",
      "addedCount": 0,
      "changedCount": 1,
      "removedCount": 0,
      "totalFiles": 518,
      "added": [],
      "changed": [
        "/pinball/data/pinball_library_v2.json"
      ],
      "removed": []
    },
    {
      "generatedAt": "2026-02-23T06:52:06.963Z",
      "addedCount": 0,
      "changedCount": 1,
      "removedCount": 0,
      "totalFiles": 518,
      "added": [],
      "changed": [
        "/pinball/data/pinball_library_v2.json"
      ],
      "removed": []
    },
    {
      "generatedAt": "2026-02-23T06:47:15.606Z",
      "addedCount": 0,
      "changedCount": 1,
      "removedCount": 0,
      "totalFiles": 518,
      "added": [],
      "changed": [
        "/pinball/data/pinball_library_v2.json"
      ],
      "removed": []
    },
    {
      "generatedAt": "2026-02-23T06:44:00.571Z",
      "addedCount": 0,
      "changedCount": 1,
      "removedCount": 0,
      "totalFiles": 518,
      "added": [],
      "changed": [
        "/pinball/data/pinball_library_v2.json"
      ],
      "removed": []
    },
    {
      "generatedAt": "2026-02-23T06:42:07.448Z",
      "addedCount": 0,
      "changedCount": 1,
      "removedCount": 0,
      "totalFiles": 518,
      "added": [],
      "changed": [
        "/pinball/data/pinball_library_v2.json"
      ],
      "removed": []
    },
    {
      "generatedAt": "2026-02-23T06:38:44.044Z",
      "addedCount": 0,
      "changedCount": 1,
      "removedCount": 0,
      "totalFiles": 518,
      "added": [],
      "changed": [
        "/pinball/data/pinball_library_v2.json"
      ],
      "removed": []
    },
    {
      "generatedAt": "2026-02-23T06:33:57.177Z",
      "addedCount": 0,
      "changedCount": 1,
      "removedCount": 0,
      "totalFiles": 518,
      "added": [],
      "changed": [
        "/pinball/data/pinball_library_v2.json"
      ],
      "removed": []
    },
    {
      "generatedAt": "2026-02-23T06:30:41.182Z",
      "addedCount": 0,
      "changedCount": 1,
      "removedCount": 0,
      "totalFiles": 518,
      "added": [],
      "changed": [
        "/pinball/data/pinball_library_v2.json"
      ],
      "removed": []
    },
    {
      "generatedAt": "2026-02-23T06:24:57.561Z",
      "addedCount": 0,
      "changedCount": 1,
      "removedCount": 0,
      "totalFiles": 518,
      "added": [],
      "changed": [
        "/pinball/data/pinball_library_v2.json"
      ],
      "removed": []
    },
    {
      "generatedAt": "2026-02-23T06:11:26.223Z",
      "addedCount": 0,
      "changedCount": 1,
      "removedCount": 0,
      "totalFiles": 518,
      "added": [],
      "changed": [
        "/pinball/data/pinball_library_v2.json"
      ],
      "removed": []
    },
    {
      "generatedAt": "2026-02-23T06:06:23.295Z",
      "addedCount": 0,
      "changedCount": 1,
      "removedCount": 0,
      "totalFiles": 518,
      "added": [],
      "changed": [
        "/pinball/data/pinball_library_v2.json"
      ],
      "removed": []
    },
    {
      "generatedAt": "2026-02-23T05:54:05.347Z",
      "addedCount": 0,
      "changedCount": 1,
      "removedCount": 0,
      "totalFiles": 518,
      "added": [],
      "changed": [
        "/pinball/data/pinball_library_v2.json"
      ],
      "removed": []
    },
    {
      "generatedAt": "2026-02-23T05:37:27.064Z",
      "addedCount": 0,
      "changedCount": 1,
      "removedCount": 0,
      "totalFiles": 518,
      "added": [],
      "changed": [
        "/pinball/data/pinball_library_v2.json"
      ],
      "removed": []
    },
    {
      "generatedAt": "2026-02-23T05:37:00.318Z",
      "addedCount": 0,
      "changedCount": 1,
      "removedCount": 0,
      "totalFiles": 518,
      "added": [],
      "changed": [
        "/pinball/data/pinball_library_v2.json"
      ],
      "removed": []
    },
    {
      "generatedAt": "2026-02-23T05:34:24.209Z",
      "addedCount": 0,
      "changedCount": 1,
      "removedCount": 0,
      "totalFiles": 518,
      "added": [],
      "changed": [
        "/pinball/data/pinball_library_v2.json"
      ],
      "removed": []
    },
    {
      "generatedAt": "2026-02-23T05:17:17.971Z",
      "addedCount": 0,
      "changedCount": 21,
      "removedCount": 0,
      "totalFiles": 518,
      "added": [],
      "changed": [
        "/pinball/gameinfo/bally--flash-gordon--1980-gameinfo.md",
        "/pinball/gameinfo/bally--indianapolis-500--1995-gameinfo.md",
        "/pinball/gameinfo/bally--nitro-ground-shaker--1980-gameinfo.md",
        "/pinball/gameinfo/bally--paragon--1979-gameinfo.md",
        "/pinball/gameinfo/bof--barrels-of-fun-labyrinth--2023-gameinfo.md",
        "/pinball/gameinfo/bof--dune--2025-gameinfo.md",
        "/pinball/gameinfo/de--tales-from-the-crypt--1993-gameinfo.md",
        "/pinball/gameinfo/gottlieb--buck-rogers--1980-gameinfo.md",
        "/pinball/gameinfo/gottlieb--excalibur--1988-gameinfo.md",
        "/pinball/gameinfo/gottlieb--fast-draw--1975-gameinfo.md",
        "/pinball/gameinfo/gottlieb--genesis--1986-gameinfo.md",
        "/pinball/gameinfo/gottlieb--robo-war--1988-gameinfo.md",
        "/pinball/gameinfo/gottlieb--totem--1979-gameinfo.md",
        "/pinball/gameinfo/jjp--harry-potter--2025-gameinfo.md",
        "/pinball/gameinfo/midway--baby-pac-man--1982-gameinfo.md",
        "/pinball/gameinfo/midway--shadow--1994-gameinfo.md",
        "/pinball/gameinfo/pb--alien--2022-gameinfo.md",
        "/pinball/gameinfo/spooky--evil-dead--2024-gameinfo.md",
        "/pinball/gameinfo/spooky--total-nuclear-annihilation--2017-gameinfo.md",
        "/pinball/gameinfo/stern--metallica-remastered--2024-gameinfo.md",
        "/pinball/gameinfo/williams--alien-poker--1980-gameinfo.md"
      ],
      "removed": []
    },
    {
      "generatedAt": "2026-02-23T05:14:21.414Z",
      "addedCount": 94,
      "changedCount": 0,
      "removedCount": 0,
      "totalFiles": 518,
      "added": [
        "/pinball/gameinfo/bally--flash-gordon--1980-gameinfo.md",
        "/pinball/gameinfo/bally--indianapolis-500--1995-gameinfo.md",
        "/pinball/gameinfo/bally--nitro-ground-shaker--1980-gameinfo.md",
        "/pinball/gameinfo/bally--paragon--1979-gameinfo.md",
        "/pinball/gameinfo/bof--barrels-of-fun-labyrinth--2023-gameinfo.md",
        "/pinball/gameinfo/bof--dune--2025-gameinfo.md",
        "/pinball/gameinfo/de--tales-from-the-crypt--1993-gameinfo.md",
        "/pinball/gameinfo/gottlieb--buck-rogers--1980-gameinfo.md",
        "/pinball/gameinfo/gottlieb--excalibur--1988-gameinfo.md",
        "/pinball/gameinfo/gottlieb--fast-draw--1975-gameinfo.md",
        "/pinball/gameinfo/gottlieb--genesis--1986-gameinfo.md",
        "/pinball/gameinfo/gottlieb--robo-war--1988-gameinfo.md",
        "/pinball/gameinfo/gottlieb--totem--1979-gameinfo.md",
        "/pinball/gameinfo/jjp--harry-potter--2025-gameinfo.md",
        "/pinball/gameinfo/midway--baby-pac-man--1982-gameinfo.md",
        "/pinball/gameinfo/midway--shadow--1994-gameinfo.md",
        "/pinball/gameinfo/pb--alien--2022-gameinfo.md",
        "/pinball/gameinfo/spooky--evil-dead--2024-gameinfo.md",
        "/pinball/gameinfo/spooky--total-nuclear-annihilation--2017-gameinfo.md",
        "/pinball/gameinfo/stern--king-kong-myth-of-terror-island--2025-gameinfo.md",
        "/pinball/gameinfo/stern--metallica-remastered--2024-gameinfo.md",
        "/pinball/gameinfo/stern--munsters--2019-gameinfo.md",
        "/pinball/gameinfo/williams--alien-poker--1980-gameinfo.md",
        "/pinball/images/playfields/bally--flash-gordon--1980-playfield.jpg",
        "/pinball/images/playfields/bally--flash-gordon--1980-playfield_1400.webp",
        "/pinball/images/playfields/bally--flash-gordon--1980-playfield_700.webp",
        "/pinball/images/playfields/bally--indianapolis-500--1995-playfield.jpg",
        "/pinball/images/playfields/bally--indianapolis-500--1995-playfield_1400.webp",
        "/pinball/images/playfields/bally--indianapolis-500--1995-playfield_700.webp",
        "/pinball/images/playfields/bally--nitro-ground-shaker--1980-playfield.jpg",
        "/pinball/images/playfields/bally--nitro-ground-shaker--1980-playfield_1400.webp",
        "/pinball/images/playfields/bally--nitro-ground-shaker--1980-playfield_700.webp",
        "/pinball/images/playfields/bally--paragon--1979-playfield.jpg",
        "/pinball/images/playfields/bally--paragon--1979-playfield_1400.webp",
        "/pinball/images/playfields/bally--paragon--1979-playfield_700.webp",
        "/pinball/images/playfields/bof--barrels-of-fun-labyrinth--2023-playfield.jpg",
        "/pinball/images/playfields/bof--barrels-of-fun-labyrinth--2023-playfield_1400.webp",
        "/pinball/images/playfields/bof--barrels-of-fun-labyrinth--2023-playfield_700.webp",
        "/pinball/images/playfields/bof--dune--2025-playfield.jpg",
        "/pinball/images/playfields/bof--dune--2025-playfield_1400.webp",
        "/pinball/images/playfields/bof--dune--2025-playfield_700.webp",
        "/pinball/images/playfields/de--tales-from-the-crypt--1993-playfield.jpg",
        "/pinball/images/playfields/de--tales-from-the-crypt--1993-playfield_1400.webp",
        "/pinball/images/playfields/de--tales-from-the-crypt--1993-playfield_700.webp",
        "/pinball/images/playfields/gottlieb--buck-rogers--1980-playfield.jpg",
        "/pinball/images/playfields/gottlieb--buck-rogers--1980-playfield_1400.webp",
        "/pinball/images/playfields/gottlieb--buck-rogers--1980-playfield_700.webp",
        "/pinball/images/playfields/gottlieb--excalibur--1988-playfield.jpg",
        "/pinball/images/playfields/gottlieb--excalibur--1988-playfield_1400.webp",
        "/pinball/images/playfields/gottlieb--excalibur--1988-playfield_700.webp",
        "/pinball/images/playfields/gottlieb--fast-draw--1975-playfield.jpg",
        "/pinball/images/playfields/gottlieb--fast-draw--1975-playfield_1400.webp",
        "/pinball/images/playfields/gottlieb--fast-draw--1975-playfield_700.webp",
        "/pinball/images/playfields/gottlieb--genesis--1986-playfield.jpg",
        "/pinball/images/playfields/gottlieb--genesis--1986-playfield_1400.webp",
        "/pinball/images/playfields/gottlieb--genesis--1986-playfield_700.webp",
        "/pinball/images/playfields/gottlieb--robo-war--1988-playfield.webp",
        "/pinball/images/playfields/gottlieb--robo-war--1988-playfield_1400.webp",
        "/pinball/images/playfields/gottlieb--robo-war--1988-playfield_700.webp",
        "/pinball/images/playfields/gottlieb--totem--1979-playfield.jpg",
        "/pinball/images/playfields/gottlieb--totem--1979-playfield_1400.webp",
        "/pinball/images/playfields/gottlieb--totem--1979-playfield_700.webp",
        "/pinball/images/playfields/jjp--harry-potter--2025-playfield.webp",
        "/pinball/images/playfields/jjp--harry-potter--2025-playfield_1400.webp",
        "/pinball/images/playfields/jjp--harry-potter--2025-playfield_700.webp",
        "/pinball/images/playfields/midway--baby-pac-man--1982-playfield.jpeg",
        "/pinball/images/playfields/midway--baby-pac-man--1982-playfield_1400.webp",
        "/pinball/images/playfields/midway--baby-pac-man--1982-playfield_700.webp",
        "/pinball/images/playfields/midway--shadow--1994-playfield.jpg",
        "/pinball/images/playfields/midway--shadow--1994-playfield_1400.webp",
        "/pinball/images/playfields/midway--shadow--1994-playfield_700.webp",
        "/pinball/images/playfields/pb--alien--2022-playfield.jpg",
        "/pinball/images/playfields/pb--alien--2022-playfield_1400.webp",
        "/pinball/images/playfields/pb--alien--2022-playfield_700.webp",
        "/pinball/images/playfields/spooky--evil-dead--2024-playfield.png",
        "/pinball/images/playfields/spooky--evil-dead--2024-playfield_1400.webp",
        "/pinball/images/playfields/spooky--evil-dead--2024-playfield_700.webp",
        "/pinball/images/playfields/spooky--total-nuclear-annihilation--2017-playfield.jpg",
        "/pinball/images/playfields/spooky--total-nuclear-annihilation--2017-playfield_1400.webp",
        "/pinball/images/playfields/spooky--total-nuclear-annihilation--2017-playfield_700.webp",
        "/pinball/images/playfields/stern--king-kong-myth-of-terror-island--2025-playfield.jpg",
        "/pinball/images/playfields/stern--king-kong-myth-of-terror-island--2025-playfield_1400.webp",
        "/pinball/images/playfields/stern--king-kong-myth-of-terror-island--2025-playfield_700.webp",
        "/pinball/images/playfields/stern--metallica-remastered--2024-playfield.jpg",
        "/pinball/images/playfields/stern--metallica-remastered--2024-playfield_1400.webp",
        "/pinball/images/playfields/stern--metallica-remastered--2024-playfield_700.webp",
        "/pinball/images/playfields/stern--munsters--2019-playfield.jpg",
        "/pinball/images/playfields/stern--munsters--2019-playfield_1400.webp",
        "/pinball/images/playfields/stern--munsters--2019-playfield_700.webp",
        "/pinball/images/playfields/williams--alien-poker--1980-playfield.jpg",
        "/pinball/images/playfields/williams--alien-poker--1980-playfield_1400.webp",
        "/pinball/images/playfields/williams--alien-poker--1980-playfield_700.webp",
        "/pinball/rulesheets/stern--king-kong-myth-of-terror-island--2025-rulesheet.md",
        "/pinball/rulesheets/stern--munsters--2019-rulesheet.md"
      ],
      "changed": [],
      "removed": []
    },
    {
      "generatedAt": "2026-02-23T04:41:36.728Z",
      "addedCount": 120,
      "changedCount": 0,
      "removedCount": 0,
      "totalFiles": 424,
      "added": [
        "/pinball/gameinfo/bally--addams-family-the--1992-gameinfo.md",
        "/pinball/gameinfo/cgc--pulp-fiction--2024-gameinfo.md",
        "/pinball/gameinfo/stern--black-knight-sword-of-rage--2019-gameinfo.md",
        "/pinball/gameinfo/stern--deadpool--2018-gameinfo.md",
        "/pinball/gameinfo/stern--dungeons-and-dragons--2025-gameinfo.md",
        "/pinball/gameinfo/stern--elviras-house-of-horrors--2019-gameinfo.md",
        "/pinball/gameinfo/stern--game-of-thrones--2015-gameinfo.md",
        "/pinball/gameinfo/stern--ghostbusters--2016-gameinfo.md",
        "/pinball/gameinfo/stern--godzilla--2021-gameinfo.md",
        "/pinball/gameinfo/stern--iron-maiden-legacy-of-the-beast--2018-gameinfo.md",
        "/pinball/gameinfo/stern--james-bond-007--2022-gameinfo.md",
        "/pinball/gameinfo/stern--jaws--2024-gameinfo.md",
        "/pinball/gameinfo/stern--john-wick--2024-gameinfo.md",
        "/pinball/gameinfo/stern--jurassic-park-stern--2019-gameinfo.md",
        "/pinball/gameinfo/stern--kiss--2015-gameinfo.md",
        "/pinball/gameinfo/stern--simpsons-pinball-party--2003-gameinfo.md",
        "/pinball/gameinfo/stern--star-wars-fall-of-the-empire--2025-gameinfo.md",
        "/pinball/gameinfo/stern--stranger-things--2019-gameinfo.md",
        "/pinball/gameinfo/stern--teenage-mutant-ninja-turtles--2020-gameinfo.md",
        "/pinball/gameinfo/stern--tron-legacy--2011-gameinfo.md",
        "/pinball/gameinfo/stern--uncanny-x-men--2024-gameinfo.md",
        "/pinball/gameinfo/stern--venom--2023-gameinfo.md",
        "/pinball/gameinfo/williams--getaway-high-speed-ii--1992-gameinfo.md",
        "/pinball/gameinfo/williams--indiana-jones--1993-gameinfo.md",
        "/pinball/images/playfields/bally--addams-family-the--1992-playfield.jpg",
        "/pinball/images/playfields/bally--addams-family-the--1992-playfield_1400.webp",
        "/pinball/images/playfields/bally--addams-family-the--1992-playfield_700.webp",
        "/pinball/images/playfields/cgc--pulp-fiction--2024-playfield.jpg",
        "/pinball/images/playfields/cgc--pulp-fiction--2024-playfield_1400.webp",
        "/pinball/images/playfields/cgc--pulp-fiction--2024-playfield_700.webp",
        "/pinball/images/playfields/stern--black-knight-sword-of-rage--2019-playfield.jpg",
        "/pinball/images/playfields/stern--black-knight-sword-of-rage--2019-playfield_1400.webp",
        "/pinball/images/playfields/stern--black-knight-sword-of-rage--2019-playfield_700.webp",
        "/pinball/images/playfields/stern--deadpool--2018-playfield.png",
        "/pinball/images/playfields/stern--deadpool--2018-playfield_1400.webp",
        "/pinball/images/playfields/stern--deadpool--2018-playfield_700.webp",
        "/pinball/images/playfields/stern--dungeons-and-dragons--2025-playfield.jpg",
        "/pinball/images/playfields/stern--dungeons-and-dragons--2025-playfield_1400.webp",
        "/pinball/images/playfields/stern--dungeons-and-dragons--2025-playfield_700.webp",
        "/pinball/images/playfields/stern--elviras-house-of-horrors--2019-playfield.jpg",
        "/pinball/images/playfields/stern--elviras-house-of-horrors--2019-playfield_1400.webp",
        "/pinball/images/playfields/stern--elviras-house-of-horrors--2019-playfield_700.webp",
        "/pinball/images/playfields/stern--game-of-thrones--2015-playfield.jpg",
        "/pinball/images/playfields/stern--game-of-thrones--2015-playfield_1400.webp",
        "/pinball/images/playfields/stern--game-of-thrones--2015-playfield_700.webp",
        "/pinball/images/playfields/stern--ghostbusters--2016-playfield.png",
        "/pinball/images/playfields/stern--ghostbusters--2016-playfield_1400.webp",
        "/pinball/images/playfields/stern--ghostbusters--2016-playfield_700.webp",
        "/pinball/images/playfields/stern--godzilla--2021-playfield.jpg",
        "/pinball/images/playfields/stern--godzilla--2021-playfield_1400.webp",
        "/pinball/images/playfields/stern--godzilla--2021-playfield_700.webp",
        "/pinball/images/playfields/stern--iron-maiden-legacy-of-the-beast--2018-playfield.png",
        "/pinball/images/playfields/stern--iron-maiden-legacy-of-the-beast--2018-playfield_1400.webp",
        "/pinball/images/playfields/stern--iron-maiden-legacy-of-the-beast--2018-playfield_700.webp",
        "/pinball/images/playfields/stern--james-bond-007--2022-playfield.jpg",
        "/pinball/images/playfields/stern--james-bond-007--2022-playfield_1400.webp",
        "/pinball/images/playfields/stern--james-bond-007--2022-playfield_700.webp",
        "/pinball/images/playfields/stern--jaws--2024-playfield.jpg",
        "/pinball/images/playfields/stern--jaws--2024-playfield_1400.webp",
        "/pinball/images/playfields/stern--jaws--2024-playfield_700.webp",
        "/pinball/images/playfields/stern--john-wick--2024-playfield.jpg",
        "/pinball/images/playfields/stern--john-wick--2024-playfield_1400.webp",
        "/pinball/images/playfields/stern--john-wick--2024-playfield_700.webp",
        "/pinball/images/playfields/stern--jurassic-park-stern--2019-playfield.jpg",
        "/pinball/images/playfields/stern--jurassic-park-stern--2019-playfield_1400.webp",
        "/pinball/images/playfields/stern--jurassic-park-stern--2019-playfield_700.webp",
        "/pinball/images/playfields/stern--kiss--2015-playfield.jpg",
        "/pinball/images/playfields/stern--kiss--2015-playfield_1400.webp",
        "/pinball/images/playfields/stern--kiss--2015-playfield_700.webp",
        "/pinball/images/playfields/stern--simpsons-pinball-party--2003-playfield.jpg",
        "/pinball/images/playfields/stern--simpsons-pinball-party--2003-playfield_1400.webp",
        "/pinball/images/playfields/stern--simpsons-pinball-party--2003-playfield_700.webp",
        "/pinball/images/playfields/stern--star-wars-fall-of-the-empire--2025-playfield.jpg",
        "/pinball/images/playfields/stern--star-wars-fall-of-the-empire--2025-playfield_1400.webp",
        "/pinball/images/playfields/stern--star-wars-fall-of-the-empire--2025-playfield_700.webp",
        "/pinball/images/playfields/stern--stranger-things--2019-playfield.jpg",
        "/pinball/images/playfields/stern--stranger-things--2019-playfield_1400.webp",
        "/pinball/images/playfields/stern--stranger-things--2019-playfield_700.webp",
        "/pinball/images/playfields/stern--teenage-mutant-ninja-turtles--2020-playfield.jpg",
        "/pinball/images/playfields/stern--teenage-mutant-ninja-turtles--2020-playfield_1400.webp",
        "/pinball/images/playfields/stern--teenage-mutant-ninja-turtles--2020-playfield_700.webp",
        "/pinball/images/playfields/stern--tron-legacy--2011-playfield.jpg",
        "/pinball/images/playfields/stern--tron-legacy--2011-playfield_1400.webp",
        "/pinball/images/playfields/stern--tron-legacy--2011-playfield_700.webp",
        "/pinball/images/playfields/stern--uncanny-x-men--2024-playfield.jpg",
        "/pinball/images/playfields/stern--uncanny-x-men--2024-playfield_1400.webp",
        "/pinball/images/playfields/stern--uncanny-x-men--2024-playfield_700.webp",
        "/pinball/images/playfields/stern--venom--2023-playfield.jpg",
        "/pinball/images/playfields/stern--venom--2023-playfield_1400.webp",
        "/pinball/images/playfields/stern--venom--2023-playfield_700.webp",
        "/pinball/images/playfields/williams--getaway-high-speed-ii--1992-playfield.jpg",
        "/pinball/images/playfields/williams--getaway-high-speed-ii--1992-playfield_1400.webp",
        "/pinball/images/playfields/williams--getaway-high-speed-ii--1992-playfield_700.webp",
        "/pinball/images/playfields/williams--indiana-jones--1993-playfield.jpg",
        "/pinball/images/playfields/williams--indiana-jones--1993-playfield_1400.webp",
        "/pinball/images/playfields/williams--indiana-jones--1993-playfield_700.webp",
        "/pinball/rulesheets/bally--addams-family-the--1992-rulesheet.md",
        "/pinball/rulesheets/cgc--pulp-fiction--2024-rulesheet.md",
        "/pinball/rulesheets/stern--black-knight-sword-of-rage--2019-rulesheet.md",
        "/pinball/rulesheets/stern--deadpool--2018-rulesheet.md",
        "/pinball/rulesheets/stern--dungeons-and-dragons--2025-rulesheet.md",
        "/pinball/rulesheets/stern--elviras-house-of-horrors--2019-rulesheet.md",
        "/pinball/rulesheets/stern--game-of-thrones--2015-rulesheet.md",
        "/pinball/rulesheets/stern--ghostbusters--2016-rulesheet.md",
        "/pinball/rulesheets/stern--godzilla--2021-rulesheet.md",
        "/pinball/rulesheets/stern--iron-maiden-legacy-of-the-beast--2018-rulesheet.md",
        "/pinball/rulesheets/stern--james-bond-007--2022-rulesheet.md",
        "/pinball/rulesheets/stern--jaws--2024-rulesheet.md",
        "/pinball/rulesheets/stern--john-wick--2024-rulesheet.md",
        "/pinball/rulesheets/stern--jurassic-park-stern--2019-rulesheet.md",
        "/pinball/rulesheets/stern--kiss--2015-rulesheet.md",
        "/pinball/rulesheets/stern--simpsons-pinball-party--2003-rulesheet.md",
        "/pinball/rulesheets/stern--star-wars-fall-of-the-empire--2025-rulesheet.md",
        "/pinball/rulesheets/stern--stranger-things--2019-rulesheet.md",
        "/pinball/rulesheets/stern--teenage-mutant-ninja-turtles--2020-rulesheet.md",
        "/pinball/rulesheets/stern--tron-legacy--2011-rulesheet.md",
        "/pinball/rulesheets/stern--uncanny-x-men--2024-rulesheet.md",
        "/pinball/rulesheets/stern--venom--2023-rulesheet.md",
        "/pinball/rulesheets/williams--getaway-high-speed-ii--1992-rulesheet.md",
        "/pinball/rulesheets/williams--indiana-jones--1993-rulesheet.md"
      ],
      "changed": [],
      "removed": []
    },
    {
      "generatedAt": "2026-02-23T04:37:11.289Z",
      "addedCount": 35,
      "changedCount": 0,
      "removedCount": 0,
      "totalFiles": 304,
      "added": [
        "/pinball/gameinfo/stern--ac-dc--2012-gameinfo.md",
        "/pinball/gameinfo/stern--avengers-infinity-quest--2020-gameinfo.md",
        "/pinball/gameinfo/stern--foo-fighters--2023-gameinfo.md",
        "/pinball/gameinfo/stern--rush--2022-gameinfo.md",
        "/pinball/gameinfo/stern--star-trek--2013-gameinfo.md",
        "/pinball/gameinfo/stern--star-wars--2017-gameinfo.md",
        "/pinball/gameinfo/stern--the-mandalorian--2021-gameinfo.md",
        "/pinball/images/playfields/stern--ac-dc--2012-playfield.jpg",
        "/pinball/images/playfields/stern--ac-dc--2012-playfield_1400.webp",
        "/pinball/images/playfields/stern--ac-dc--2012-playfield_700.webp",
        "/pinball/images/playfields/stern--avengers-infinity-quest--2020-playfield.jpg",
        "/pinball/images/playfields/stern--avengers-infinity-quest--2020-playfield_1400.webp",
        "/pinball/images/playfields/stern--avengers-infinity-quest--2020-playfield_700.webp",
        "/pinball/images/playfields/stern--foo-fighters--2023-playfield.jpg",
        "/pinball/images/playfields/stern--foo-fighters--2023-playfield_1400.webp",
        "/pinball/images/playfields/stern--foo-fighters--2023-playfield_700.webp",
        "/pinball/images/playfields/stern--rush--2022-playfield.jpg",
        "/pinball/images/playfields/stern--rush--2022-playfield_1400.webp",
        "/pinball/images/playfields/stern--rush--2022-playfield_700.webp",
        "/pinball/images/playfields/stern--star-trek--2013-playfield.jpg",
        "/pinball/images/playfields/stern--star-trek--2013-playfield_1400.webp",
        "/pinball/images/playfields/stern--star-trek--2013-playfield_700.webp",
        "/pinball/images/playfields/stern--star-wars--2017-playfield.png",
        "/pinball/images/playfields/stern--star-wars--2017-playfield_1400.webp",
        "/pinball/images/playfields/stern--star-wars--2017-playfield_700.webp",
        "/pinball/images/playfields/stern--the-mandalorian--2021-playfield.jpg",
        "/pinball/images/playfields/stern--the-mandalorian--2021-playfield_1400.webp",
        "/pinball/images/playfields/stern--the-mandalorian--2021-playfield_700.webp",
        "/pinball/rulesheets/stern--ac-dc--2012-rulesheet.md",
        "/pinball/rulesheets/stern--avengers-infinity-quest--2020-rulesheet.md",
        "/pinball/rulesheets/stern--foo-fighters--2023-rulesheet.md",
        "/pinball/rulesheets/stern--rush--2022-rulesheet.md",
        "/pinball/rulesheets/stern--star-trek--2013-rulesheet.md",
        "/pinball/rulesheets/stern--star-wars--2017-rulesheet.md",
        "/pinball/rulesheets/stern--the-mandalorian--2021-rulesheet.md"
      ],
      "changed": [],
      "removed": []
    },
    {
      "generatedAt": "2026-02-23T04:28:49.211Z",
      "addedCount": 30,
      "changedCount": 0,
      "removedCount": 0,
      "totalFiles": 269,
      "added": [
        "/pinball/gameinfo/bally--attack-from-mars--1995-gameinfo.md",
        "/pinball/gameinfo/bally--cactus-canyon--1998-gameinfo.md",
        "/pinball/gameinfo/bally--scared-stiff--1996-gameinfo.md",
        "/pinball/gameinfo/stern--metallica--2013-gameinfo.md",
        "/pinball/gameinfo/williams--medieval-madness--1997-gameinfo.md",
        "/pinball/gameinfo/williams--monster-bash--1998-gameinfo.md",
        "/pinball/images/playfields/bally--attack-from-mars--1995-playfield.jpg",
        "/pinball/images/playfields/bally--attack-from-mars--1995-playfield_1400.webp",
        "/pinball/images/playfields/bally--attack-from-mars--1995-playfield_700.webp",
        "/pinball/images/playfields/bally--cactus-canyon--1998-playfield.jpg",
        "/pinball/images/playfields/bally--cactus-canyon--1998-playfield_1400.webp",
        "/pinball/images/playfields/bally--cactus-canyon--1998-playfield_700.webp",
        "/pinball/images/playfields/bally--scared-stiff--1996-playfield.jpg",
        "/pinball/images/playfields/bally--scared-stiff--1996-playfield_1400.webp",
        "/pinball/images/playfields/bally--scared-stiff--1996-playfield_700.webp",
        "/pinball/images/playfields/stern--metallica--2013-playfield.jpg",
        "/pinball/images/playfields/stern--metallica--2013-playfield_1400.webp",
        "/pinball/images/playfields/stern--metallica--2013-playfield_700.webp",
        "/pinball/images/playfields/williams--medieval-madness--1997-playfield.jpg",
        "/pinball/images/playfields/williams--medieval-madness--1997-playfield_1400.webp",
        "/pinball/images/playfields/williams--medieval-madness--1997-playfield_700.webp",
        "/pinball/images/playfields/williams--monster-bash--1998-playfield.jpg",
        "/pinball/images/playfields/williams--monster-bash--1998-playfield_1400.webp",
        "/pinball/images/playfields/williams--monster-bash--1998-playfield_700.webp",
        "/pinball/rulesheets/bally--attack-from-mars--1995-rulesheet.md",
        "/pinball/rulesheets/bally--cactus-canyon--1998-rulesheet.md",
        "/pinball/rulesheets/bally--scared-stiff--1996-rulesheet.md",
        "/pinball/rulesheets/stern--metallica--2013-rulesheet.md",
        "/pinball/rulesheets/williams--medieval-madness--1997-rulesheet.md",
        "/pinball/rulesheets/williams--monster-bash--1998-rulesheet.md"
      ],
      "changed": [],
      "removed": []
    },
    {
      "generatedAt": "2026-02-23T04:17:18.771Z",
      "addedCount": 0,
      "changedCount": 0,
      "removedCount": 0,
      "totalFiles": 239,
      "added": [],
      "changed": [],
      "removed": []
    },
    {
      "generatedAt": "2026-02-23T04:15:45.379Z",
      "addedCount": 6,
      "changedCount": 7,
      "removedCount": 0,
      "totalFiles": 239,
      "added": [
        "/pinball/data/codex_missing_group_fetch_targets.json",
        "/pinball/data/pinside_link_audit_report.json",
        "/pinball/data/pinside_resolved_machine_map.final.json",
        "/pinball/data/pinside_resolved_machine_map.json",
        "/pinball/images/playfields/fallback-whitewood-playfield_1400.webp",
        "/pinball/images/playfields/fallback-whitewood-playfield_700.webp"
      ],
      "changed": [
        "/pinball/data/Avenue Pinball - Current.csv",
        "/pinball/data/Codex Pinball Library - Current.csv",
        "/pinball/data/RLM Amusements - Current.csv",
        "/pinball/data/pinball_library.json",
        "/pinball/data/pinball_library_v2.json",
        "/pinball/data/pinside_group_map.json",
        "/pinball/images/.DS_Store"
      ],
      "removed": []
    },
    {
      "generatedAt": "2026-02-22T19:41:24.780Z",
      "addedCount": 18,
      "changedCount": 3,
      "removedCount": 0,
      "totalFiles": 233,
      "added": [
        "/pinball/data/Codex Pinball Library - Current.csv",
        "/pinball/data/pinball_library_v2.json",
        "/pinball/data/pinside_group_map.json",
        "/pinball/gameinfo/stern--dungeons-and-dragons-the-tyrants-eye--2025-gameinfo.md",
        "/pinball/gameinfo/williams--tales-of-the-arabian-nights--1996-gameinfo.md",
        "/pinball/gameinfo/williams--the-getaway-high-speed-ii--1992-gameinfo.md",
        "/pinball/images/playfields/stern--dungeons-and-dragons-the-tyrants-eye--2025-playfield.jpg",
        "/pinball/images/playfields/stern--dungeons-and-dragons-the-tyrants-eye--2025-playfield_1400.webp",
        "/pinball/images/playfields/stern--dungeons-and-dragons-the-tyrants-eye--2025-playfield_700.webp",
        "/pinball/images/playfields/williams--tales-of-the-arabian-nights--1996-playfield.jpg",
        "/pinball/images/playfields/williams--tales-of-the-arabian-nights--1996-playfield_1400.webp",
        "/pinball/images/playfields/williams--tales-of-the-arabian-nights--1996-playfield_700.webp",
        "/pinball/images/playfields/williams--the-getaway-high-speed-ii--1992-playfield.jpg",
        "/pinball/images/playfields/williams--the-getaway-high-speed-ii--1992-playfield_1400.webp",
        "/pinball/images/playfields/williams--the-getaway-high-speed-ii--1992-playfield_700.webp",
        "/pinball/rulesheets/stern--dungeons-and-dragons-the-tyrants-eye--2025-rulesheet.md",
        "/pinball/rulesheets/williams--tales-of-the-arabian-nights--1996-rulesheet.md",
        "/pinball/rulesheets/williams--the-getaway-high-speed-ii--1992-rulesheet.md"
      ],
      "changed": [
        "/pinball/data/Avenue Pinball - Current.csv",
        "/pinball/data/RLM Amusements - Current.csv",
        "/pinball/data/pinball_library.json"
      ],
      "removed": []
    },
    {
      "generatedAt": "2026-02-22T16:56:19.048Z",
      "addedCount": 0,
      "changedCount": 0,
      "removedCount": 0,
      "totalFiles": 215,
      "added": [],
      "changed": [],
      "removed": []
    },
    {
      "generatedAt": "2026-02-22T16:43:54.344Z",
      "addedCount": 0,
      "changedCount": 0,
      "removedCount": 0,
      "totalFiles": 215,
      "added": [],
      "changed": [],
      "removed": []
    },
    {
      "generatedAt": "2026-02-22T16:36:23.554Z",
      "addedCount": 0,
      "changedCount": 2,
      "removedCount": 0,
      "totalFiles": 215,
      "added": [],
      "changed": [
        "/pinball/data/Avenue Pinball - Current.csv",
        "/pinball/data/pinball_library.json"
      ],
      "removed": []
    },
    {
      "generatedAt": "2026-02-22T16:31:50.891Z",
      "addedCount": 0,
      "changedCount": 0,
      "removedCount": 0,
      "totalFiles": 215,
      "added": [],
      "changed": [],
      "removed": []
    },
    {
      "generatedAt": "2026-02-22T16:20:51.376Z",
      "addedCount": 0,
      "changedCount": 0,
      "removedCount": 0,
      "totalFiles": 215,
      "added": [],
      "changed": [],
      "removed": []
    },
    {
      "generatedAt": "2026-02-22T16:17:05.504Z",
      "addedCount": 0,
      "changedCount": 0,
      "removedCount": 0,
      "totalFiles": 215,
      "added": [],
      "changed": [],
      "removed": []
    },
    {
      "generatedAt": "2026-02-22T16:13:27.922Z",
      "addedCount": 0,
      "changedCount": 2,
      "removedCount": 0,
      "totalFiles": 215,
      "added": [],
      "changed": [
        "/pinball/.DS_Store",
        "/pinball/images/.DS_Store"
      ],
      "removed": []
    },
    {
      "generatedAt": "2026-02-22T16:05:29.704Z",
      "addedCount": 1,
      "changedCount": 1,
      "removedCount": 0,
      "totalFiles": 215,
      "added": [
        "/pinball/images/playfields/.DS_Store"
      ],
      "changed": [
        "/pinball/data/pinball_library.json"
      ],
      "removed": []
    },
    {
      "generatedAt": "2026-02-22T15:46:40.418Z",
      "addedCount": 1,
      "changedCount": 44,
      "removedCount": 1,
      "totalFiles": 214,
      "added": [
        "/pinball/images/playfields/metallica.jpg"
      ],
      "changed": [
        "/pinball/images/playfields/attack-from-mars.jpg",
        "/pinball/images/playfields/attack-from-mars_1400.webp",
        "/pinball/images/playfields/attack-from-mars_700.webp",
        "/pinball/images/playfields/cactus-canyon.jpg",
        "/pinball/images/playfields/cactus-canyon_1400.webp",
        "/pinball/images/playfields/cactus-canyon_700.webp",
        "/pinball/images/playfields/game-of-thrones.jpg",
        "/pinball/images/playfields/game-of-thrones_1400.webp",
        "/pinball/images/playfields/game-of-thrones_700.webp",
        "/pinball/images/playfields/indiana-jones-the-pinball-adventure.jpg",
        "/pinball/images/playfields/indiana-jones-the-pinball-adventure_1400.webp",
        "/pinball/images/playfields/indiana-jones-the-pinball-adventure_700.webp",
        "/pinball/images/playfields/kiss.jpg",
        "/pinball/images/playfields/kiss_1400.webp",
        "/pinball/images/playfields/kiss_700.webp",
        "/pinball/images/playfields/medieval-madness.jpg",
        "/pinball/images/playfields/medieval-madness_1400.webp",
        "/pinball/images/playfields/medieval-madness_700.webp",
        "/pinball/images/playfields/metallica_1400.webp",
        "/pinball/images/playfields/metallica_700.webp",
        "/pinball/images/playfields/monster-bash.jpg",
        "/pinball/images/playfields/monster-bash_1400.webp",
        "/pinball/images/playfields/monster-bash_700.webp",
        "/pinball/images/playfields/pulp-fiction.jpg",
        "/pinball/images/playfields/pulp-fiction_1400.webp",
        "/pinball/images/playfields/pulp-fiction_700.webp",
        "/pinball/images/playfields/scared-stiff.jpg",
        "/pinball/images/playfields/scared-stiff_1400.webp",
        "/pinball/images/playfields/scared-stiff_700.webp",
        "/pinball/images/playfields/tales-of-the-arabian-nights.jpg",
        "/pinball/images/playfields/tales-of-the-arabian-nights_1400.webp",
        "/pinball/images/playfields/tales-of-the-arabian-nights_700.webp",
        "/pinball/images/playfields/the-addams-family.jpg",
        "/pinball/images/playfields/the-addams-family_1400.webp",
        "/pinball/images/playfields/the-addams-family_700.webp",
        "/pinball/images/playfields/the-getaway-high-speed-ii.jpg",
        "/pinball/images/playfields/the-getaway-high-speed-ii_1400.webp",
        "/pinball/images/playfields/the-getaway-high-speed-ii_700.webp",
        "/pinball/images/playfields/the-simpsons-pinball-party.jpg",
        "/pinball/images/playfields/the-simpsons-pinball-party_1400.webp",
        "/pinball/images/playfields/the-simpsons-pinball-party_700.webp",
        "/pinball/images/playfields/tron-legacy.jpg",
        "/pinball/images/playfields/tron-legacy_1400.webp",
        "/pinball/images/playfields/tron-legacy_700.webp"
      ],
      "removed": [
        "/pinball/images/playfields/metallica.jpeg"
      ]
    },
    {
      "generatedAt": "2026-02-21T00:52:53.235Z",
      "addedCount": 0,
      "changedCount": 2,
      "removedCount": 0,
      "totalFiles": 214,
      "added": [],
      "changed": [
        "/pinball/data/Avenue Pinball - Current.csv",
        "/pinball/data/pinball_library.json"
      ],
      "removed": []
    },
    {
      "generatedAt": "2026-02-19T21:57:56.774Z",
      "addedCount": 0,
      "changedCount": 0,
      "removedCount": 0,
      "totalFiles": 214,
      "added": [],
      "changed": [],
      "removed": []
    },
    {
      "generatedAt": "2026-02-19T21:48:20.582Z",
      "addedCount": 0,
      "changedCount": 0,
      "removedCount": 0,
      "totalFiles": 214,
      "added": [],
      "changed": [],
      "removed": []
    },
    {
      "generatedAt": "2026-02-19T20:59:53.137Z",
      "addedCount": 1,
      "changedCount": 0,
      "removedCount": 0,
      "totalFiles": 214,
      "added": [
        "/pinball/data/RLM Amusements - Current.csv"
      ],
      "changed": [],
      "removed": []
    },
    {
      "generatedAt": "2026-02-19T19:57:26.045Z",
      "addedCount": 0,
      "changedCount": 2,
      "removedCount": 0,
      "totalFiles": 213,
      "added": [],
      "changed": [
        "/pinball/data/Avenue Pinball - Current.csv",
        "/pinball/data/pinball_library.json"
      ],
      "removed": []
    },
    {
      "generatedAt": "2026-02-19T18:39:01.898Z",
      "addedCount": 0,
      "changedCount": 0,
      "removedCount": 0,
      "totalFiles": 213,
      "added": [],
      "changed": [],
      "removed": []
    },
    {
      "generatedAt": "2026-02-19T18:35:34.658Z",
      "addedCount": 0,
      "changedCount": 0,
      "removedCount": 0,
      "totalFiles": 213,
      "added": [],
      "changed": [],
      "removed": []
    },
    {
      "generatedAt": "2026-02-19T18:34:36.928Z",
      "addedCount": 0,
      "changedCount": 1,
      "removedCount": 0,
      "totalFiles": 213,
      "added": [],
      "changed": [
        "/pinball/.DS_Store"
      ],
      "removed": []
    },
    {
      "generatedAt": "2026-02-19T18:09:35.597Z",
      "addedCount": 0,
      "changedCount": 0,
      "removedCount": 0,
      "totalFiles": 213,
      "added": [],
      "changed": [],
      "removed": []
    },
    {
      "generatedAt": "2026-02-19T18:08:15.584Z",
      "addedCount": 0,
      "changedCount": 12,
      "removedCount": 0,
      "totalFiles": 213,
      "added": [],
      "changed": [
        "/pinball/rulesheets/avengers-infinity-quest.md",
        "/pinball/rulesheets/dungeons-and-dragons-the-tyrants-eye.md",
        "/pinball/rulesheets/elviras-house-of-horrors.md",
        "/pinball/rulesheets/foo-fighters.md",
        "/pinball/rulesheets/game-of-thrones.md",
        "/pinball/rulesheets/jurassic-park.md",
        "/pinball/rulesheets/kiss.md",
        "/pinball/rulesheets/rush.md",
        "/pinball/rulesheets/star-trek.md",
        "/pinball/rulesheets/star-wars-fall-of-the-empire.md",
        "/pinball/rulesheets/teenage-mutant-ninja-turtles.md",
        "/pinball/rulesheets/the-munsters.md"
      ],
      "removed": []
    },
    {
      "generatedAt": "2026-02-19T17:52:37.041Z",
      "addedCount": 0,
      "changedCount": 19,
      "removedCount": 0,
      "totalFiles": 213,
      "added": [],
      "changed": [
        "/pinball/rulesheets/avengers-infinity-quest.md",
        "/pinball/rulesheets/deadpool.md",
        "/pinball/rulesheets/dungeons-and-dragons-the-tyrants-eye.md",
        "/pinball/rulesheets/foo-fighters.md",
        "/pinball/rulesheets/godzilla.md",
        "/pinball/rulesheets/james-bond-007.md",
        "/pinball/rulesheets/jaws.md",
        "/pinball/rulesheets/john-wick.md",
        "/pinball/rulesheets/jurassic-park.md",
        "/pinball/rulesheets/king-kong.md",
        "/pinball/rulesheets/metallica.md",
        "/pinball/rulesheets/rush.md",
        "/pinball/rulesheets/star-trek.md",
        "/pinball/rulesheets/star-wars-fall-of-the-empire.md",
        "/pinball/rulesheets/star-wars.md",
        "/pinball/rulesheets/teenage-mutant-ninja-turtles.md",
        "/pinball/rulesheets/the-munsters.md",
        "/pinball/rulesheets/the-uncanny-x-men.md",
        "/pinball/rulesheets/venom.md"
      ],
      "removed": []
    },
    {
      "generatedAt": "2026-02-19T17:43:39.497Z",
      "addedCount": 0,
      "changedCount": 0,
      "removedCount": 0,
      "totalFiles": 213,
      "added": [],
      "changed": [],
      "removed": []
    },
    {
      "generatedAt": "2026-02-19T17:37:53.882Z",
      "addedCount": 0,
      "changedCount": 0,
      "removedCount": 0,
      "totalFiles": 213,
      "added": [],
      "changed": [],
      "removed": []
    },
    {
      "generatedAt": "2026-02-19T17:37:39.783Z",
      "addedCount": 0,
      "changedCount": 0,
      "removedCount": 0,
      "totalFiles": 213,
      "added": [],
      "changed": [],
      "removed": []
    },
    {
      "generatedAt": "2026-02-19T17:34:37.530Z",
      "addedCount": 0,
      "changedCount": 0,
      "removedCount": 0,
      "totalFiles": 213,
      "added": [],
      "changed": [],
      "removed": []
    },
    {
      "generatedAt": "2026-02-19T17:31:25.938Z",
      "addedCount": 0,
      "changedCount": 25,
      "removedCount": 0,
      "totalFiles": 213,
      "added": [],
      "changed": [
        "/pinball/rulesheets/avengers-infinity-quest.md",
        "/pinball/rulesheets/black-knight-sword-of-rage.md",
        "/pinball/rulesheets/deadpool.md",
        "/pinball/rulesheets/dungeons-and-dragons-the-tyrants-eye.md",
        "/pinball/rulesheets/elviras-house-of-horrors.md",
        "/pinball/rulesheets/foo-fighters.md",
        "/pinball/rulesheets/godzilla.md",
        "/pinball/rulesheets/iron-maiden.md",
        "/pinball/rulesheets/james-bond-007.md",
        "/pinball/rulesheets/jaws.md",
        "/pinball/rulesheets/john-wick.md",
        "/pinball/rulesheets/jurassic-park.md",
        "/pinball/rulesheets/king-kong.md",
        "/pinball/rulesheets/metallica.md",
        "/pinball/rulesheets/pulp-fiction.md",
        "/pinball/rulesheets/rush.md",
        "/pinball/rulesheets/star-trek.md",
        "/pinball/rulesheets/star-wars-fall-of-the-empire.md",
        "/pinball/rulesheets/star-wars.md",
        "/pinball/rulesheets/stranger-things.md",
        "/pinball/rulesheets/teenage-mutant-ninja-turtles.md",
        "/pinball/rulesheets/the-mandalorian.md",
        "/pinball/rulesheets/the-munsters.md",
        "/pinball/rulesheets/the-uncanny-x-men.md",
        "/pinball/rulesheets/venom.md"
      ],
      "removed": []
    },
    {
      "generatedAt": "2026-02-19T17:16:47.966Z",
      "addedCount": 0,
      "changedCount": 0,
      "removedCount": 0,
      "totalFiles": 213,
      "added": [],
      "changed": [],
      "removed": []
    },
    {
      "generatedAt": "2026-02-19T17:14:42.938Z",
      "addedCount": 0,
      "changedCount": 0,
      "removedCount": 0,
      "totalFiles": 213,
      "added": [],
      "changed": [],
      "removed": []
    },
    {
      "generatedAt": "2026-02-19T17:08:52.781Z",
      "addedCount": 0,
      "changedCount": 0,
      "removedCount": 0,
      "totalFiles": 213,
      "added": [],
      "changed": [],
      "removed": []
    },
    {
      "generatedAt": "2026-02-19T17:06:08.054Z",
      "addedCount": 0,
      "changedCount": 1,
      "removedCount": 0,
      "totalFiles": 213,
      "added": [],
      "changed": [
        "/pinball/data/pinball_library.json"
      ],
      "removed": []
    },
    {
      "generatedAt": "2026-02-19T16:59:33.836Z",
      "addedCount": 0,
      "changedCount": 0,
      "removedCount": 0,
      "totalFiles": 213,
      "added": [],
      "changed": [],
      "removed": []
    },
    {
      "generatedAt": "2026-02-19T16:57:00.375Z",
      "addedCount": 0,
      "changedCount": 32,
      "removedCount": 0,
      "totalFiles": 213,
      "added": [],
      "changed": [
        "/pinball/.DS_Store",
        "/pinball/data/pinball_library.csv",
        "/pinball/data/pinball_library.json",
        "/pinball/rulesheets/avengers-infinity-quest.md",
        "/pinball/rulesheets/black-knight-sword-of-rage.md",
        "/pinball/rulesheets/deadpool.md",
        "/pinball/rulesheets/dungeons-and-dragons-the-tyrants-eye.md",
        "/pinball/rulesheets/elviras-house-of-horrors.md",
        "/pinball/rulesheets/foo-fighters.md",
        "/pinball/rulesheets/game-of-thrones.md",
        "/pinball/rulesheets/ghostbusters.md",
        "/pinball/rulesheets/godzilla.md",
        "/pinball/rulesheets/iron-maiden.md",
        "/pinball/rulesheets/james-bond-007.md",
        "/pinball/rulesheets/jaws.md",
        "/pinball/rulesheets/john-wick.md",
        "/pinball/rulesheets/jurassic-park.md",
        "/pinball/rulesheets/king-kong.md",
        "/pinball/rulesheets/kiss.md",
        "/pinball/rulesheets/metallica.md",
        "/pinball/rulesheets/pulp-fiction.md",
        "/pinball/rulesheets/rush.md",
        "/pinball/rulesheets/star-trek.md",
        "/pinball/rulesheets/star-wars-fall-of-the-empire.md",
        "/pinball/rulesheets/star-wars.md",
        "/pinball/rulesheets/stranger-things.md",
        "/pinball/rulesheets/teenage-mutant-ninja-turtles.md",
        "/pinball/rulesheets/the-mandalorian.md",
        "/pinball/rulesheets/the-munsters.md",
        "/pinball/rulesheets/the-uncanny-x-men.md",
        "/pinball/rulesheets/tron-legacy.md",
        "/pinball/rulesheets/venom.md"
      ],
      "removed": []
    },
    {
      "generatedAt": "2026-02-16T04:32:00.973Z",
      "addedCount": 0,
      "changedCount": 0,
      "removedCount": 0,
      "totalFiles": 213,
      "added": [],
      "changed": [],
      "removed": []
    },
    {
      "generatedAt": "2026-02-16T03:40:33.459Z",
      "addedCount": 0,
      "changedCount": 0,
      "removedCount": 0,
      "totalFiles": 213,
      "added": [],
      "changed": [],
      "removed": []
    },
    {
      "generatedAt": "2026-02-16T00:52:49.144Z",
      "addedCount": 0,
      "changedCount": 29,
      "removedCount": 0,
      "totalFiles": 213,
      "added": [],
      "changed": [
        "/pinball/data/LPL_Stats.csv",
        "/pinball/rulesheets/avengers-infinity-quest.md",
        "/pinball/rulesheets/black-knight-sword-of-rage.md",
        "/pinball/rulesheets/deadpool.md",
        "/pinball/rulesheets/dungeons-and-dragons-the-tyrants-eye.md",
        "/pinball/rulesheets/elviras-house-of-horrors.md",
        "/pinball/rulesheets/foo-fighters.md",
        "/pinball/rulesheets/game-of-thrones.md",
        "/pinball/rulesheets/ghostbusters.md",
        "/pinball/rulesheets/godzilla.md",
        "/pinball/rulesheets/iron-maiden.md",
        "/pinball/rulesheets/james-bond-007.md",
        "/pinball/rulesheets/jaws.md",
        "/pinball/rulesheets/john-wick.md",
        "/pinball/rulesheets/jurassic-park.md",
        "/pinball/rulesheets/king-kong.md",
        "/pinball/rulesheets/kiss.md",
        "/pinball/rulesheets/metallica.md",
        "/pinball/rulesheets/pulp-fiction.md",
        "/pinball/rulesheets/rush.md",
        "/pinball/rulesheets/star-trek.md",
        "/pinball/rulesheets/star-wars-fall-of-the-empire.md",
        "/pinball/rulesheets/star-wars.md",
        "/pinball/rulesheets/stranger-things.md",
        "/pinball/rulesheets/teenage-mutant-ninja-turtles.md",
        "/pinball/rulesheets/the-mandalorian.md",
        "/pinball/rulesheets/the-munsters.md",
        "/pinball/rulesheets/the-uncanny-x-men.md",
        "/pinball/rulesheets/venom.md"
      ],
      "removed": []
    },
    {
      "generatedAt": "2026-02-14T16:36:38.413Z",
      "addedCount": 0,
      "changedCount": 0,
      "removedCount": 0,
      "totalFiles": 213,
      "added": [],
      "changed": [],
      "removed": []
    },
    {
      "generatedAt": "2026-02-14T16:32:08.054Z",
      "addedCount": 0,
      "changedCount": 1,
      "removedCount": 0,
      "totalFiles": 213,
      "added": [],
      "changed": [
        "/pinball/data/LPL_Stats.csv"
      ],
      "removed": []
    },
    {
      "generatedAt": "2026-02-13T03:06:26.227Z",
      "addedCount": 0,
      "changedCount": 1,
      "removedCount": 0,
      "totalFiles": 213,
      "added": [],
      "changed": [
        "/pinball/data/LPL_Stats.csv"
      ],
      "removed": []
    },
    {
      "generatedAt": "2026-02-12T21:37:48.395Z",
      "addedCount": 0,
      "changedCount": 0,
      "removedCount": 0,
      "totalFiles": 213,
      "added": [],
      "changed": [],
      "removed": []
    },
    {
      "generatedAt": "2026-02-12T21:31:01.425Z",
      "addedCount": 0,
      "changedCount": 0,
      "removedCount": 0,
      "totalFiles": 213,
      "added": [],
      "changed": [],
      "removed": []
    },
    {
      "generatedAt": "2026-02-12T21:25:38.692Z",
      "addedCount": 0,
      "changedCount": 1,
      "removedCount": 0,
      "totalFiles": 213,
      "added": [],
      "changed": [
        "/pinball/data/redacted_players.csv"
      ],
      "removed": []
    },
    {
      "generatedAt": "2026-02-12T21:22:11.507Z",
      "addedCount": 0,
      "changedCount": 0,
      "removedCount": 0,
      "totalFiles": 213,
      "added": [],
      "changed": [],
      "removed": []
    },
    {
      "generatedAt": "2026-02-12T19:40:17.039Z",
      "addedCount": 0,
      "changedCount": 0,
      "removedCount": 0,
      "totalFiles": 213,
      "added": [],
      "changed": [],
      "removed": []
    },
    {
      "generatedAt": "2026-02-12T19:40:05.103Z",
      "addedCount": 0,
      "changedCount": 1,
      "removedCount": 0,
      "totalFiles": 213,
      "added": [],
      "changed": [
        "/pinball/data/redacted_players.csv"
      ],
      "removed": []
    },
    {
      "generatedAt": "2026-02-12T19:37:56.632Z",
      "addedCount": 1,
      "changedCount": 0,
      "removedCount": 0,
      "totalFiles": 213,
      "added": [
        "/pinball/data/redacted_players.csv"
      ],
      "changed": [],
      "removed": []
    },
    {
      "generatedAt": "2026-02-11T08:50:55.461Z",
      "addedCount": 0,
      "changedCount": 0,
      "removedCount": 0,
      "totalFiles": 212,
      "added": [],
      "changed": [],
      "removed": []
    },
    {
      "generatedAt": "2026-02-11T08:48:54.863Z",
      "addedCount": 0,
      "changedCount": 1,
      "removedCount": 0,
      "totalFiles": 212,
      "added": [],
      "changed": [
        "/pinball/data/LPL_Stats.csv"
      ],
      "removed": []
    },
    {
      "generatedAt": "2026-02-11T06:54:59.635Z",
      "addedCount": 0,
      "changedCount": 2,
      "removedCount": 0,
      "totalFiles": 212,
      "added": [],
      "changed": [
        "/pinball/data/LPL_Standings.csv",
        "/pinball/data/LPL_Stats.csv"
      ],
      "removed": []
    },
    {
      "generatedAt": "2026-02-09T17:04:07.903Z",
      "addedCount": 0,
      "changedCount": 0,
      "removedCount": 0,
      "totalFiles": 212,
      "added": [],
      "changed": [],
      "removed": []
    },
    {
      "generatedAt": "2026-02-09T16:57:19.433Z",
      "addedCount": 0,
      "changedCount": 0,
      "removedCount": 0,
      "totalFiles": 212,
      "added": [],
      "changed": [],
      "removed": []
    },
    {
      "generatedAt": "2026-02-09T16:51:01.969Z",
      "addedCount": 0,
      "changedCount": 0,
      "removedCount": 0,
      "totalFiles": 212,
      "added": [],
      "changed": [],
      "removed": []
    },
    {
      "generatedAt": "2026-02-09T16:45:48.737Z",
      "addedCount": 0,
      "changedCount": 0,
      "removedCount": 0,
      "totalFiles": 212,
      "added": [],
      "changed": [],
      "removed": []
    },
    {
      "generatedAt": "2026-02-09T13:36:15.676Z",
      "addedCount": 0,
      "changedCount": 0,
      "removedCount": 0,
      "totalFiles": 212,
      "added": [],
      "changed": [],
      "removed": []
    },
    {
      "generatedAt": "2026-02-09T13:32:16.690Z",
      "addedCount": 0,
      "changedCount": 0,
      "removedCount": 0,
      "totalFiles": 212,
      "added": [],
      "changed": [],
      "removed": []
    },
    {
      "generatedAt": "2026-02-09T04:13:45.457Z",
      "addedCount": 0,
      "changedCount": 0,
      "removedCount": 0,
      "totalFiles": 212,
      "added": [],
      "changed": [],
      "removed": []
    },
    {
      "generatedAt": "2026-02-09T03:13:37.721Z",
      "addedCount": 0,
      "changedCount": 0,
      "removedCount": 0,
      "totalFiles": 212,
      "added": [],
      "changed": [],
      "removed": []
    },
    {
      "generatedAt": "2026-02-09T02:56:23.687Z",
      "addedCount": 0,
      "changedCount": 0,
      "removedCount": 0,
      "totalFiles": 212,
      "added": [],
      "changed": [],
      "removed": []
    },
    {
      "generatedAt": "2026-02-09T02:50:45.577Z",
      "addedCount": 0,
      "changedCount": 0,
      "removedCount": 0,
      "totalFiles": 212,
      "added": [],
      "changed": [],
      "removed": []
    },
    {
      "generatedAt": "2026-02-09T02:31:29.939Z",
      "addedCount": 0,
      "changedCount": 0,
      "removedCount": 0,
      "totalFiles": 212,
      "added": [],
      "changed": [],
      "removed": []
    },
    {
      "generatedAt": "2026-02-09T02:07:21.775Z",
      "addedCount": 0,
      "changedCount": 0,
      "removedCount": 0,
      "totalFiles": 212,
      "added": [],
      "changed": [],
      "removed": []
    },
    {
      "generatedAt": "2026-02-09T02:03:50.705Z",
      "addedCount": 0,
      "changedCount": 0,
      "removedCount": 0,
      "totalFiles": 212,
      "added": [],
      "changed": [],
      "removed": []
    },
    {
      "generatedAt": "2026-02-09T01:46:02.553Z",
      "addedCount": 0,
      "changedCount": 0,
      "removedCount": 0,
      "totalFiles": 212,
      "added": [],
      "changed": [],
      "removed": []
    },
    {
      "generatedAt": "2026-02-09T00:53:33.505Z",
      "addedCount": 0,
      "changedCount": 0,
      "removedCount": 0,
      "totalFiles": 212,
      "added": [],
      "changed": [],
      "removed": []
    },
    {
      "generatedAt": "2026-02-08T23:24:57.948Z",
      "addedCount": 0,
      "changedCount": 0,
      "removedCount": 0,
      "totalFiles": 212,
      "added": [],
      "changed": [],
      "removed": []
    },
    {
      "generatedAt": "2026-02-08T23:21:12.519Z",
      "addedCount": 0,
      "changedCount": 0,
      "removedCount": 0,
      "totalFiles": 212,
      "added": [],
      "changed": [],
      "removed": []
    },
    {
      "generatedAt": "2026-02-08T23:14:34.354Z",
      "addedCount": 0,
      "changedCount": 0,
      "removedCount": 0,
      "totalFiles": 212,
      "added": [],
      "changed": [],
      "removed": []
    },
    {
      "generatedAt": "2026-02-08T23:12:16.832Z",
      "addedCount": 0,
      "changedCount": 0,
      "removedCount": 0,
      "totalFiles": 212,
      "added": [],
      "changed": [],
      "removed": []
    },
    {
      "generatedAt": "2026-02-08T23:00:34.305Z",
      "addedCount": 0,
      "changedCount": 0,
      "removedCount": 0,
      "totalFiles": 212,
      "added": [],
      "changed": [],
      "removed": []
    },
    {
      "generatedAt": "2026-02-08T22:58:10.788Z",
      "addedCount": 0,
      "changedCount": 0,
      "removedCount": 0,
      "totalFiles": 212,
      "added": [],
      "changed": [],
      "removed": []
    },
    {
      "generatedAt": "2026-02-08T22:52:17.300Z",
      "addedCount": 0,
      "changedCount": 0,
      "removedCount": 0,
      "totalFiles": 212,
      "added": [],
      "changed": [],
      "removed": []
    },
    {
      "generatedAt": "2026-02-08T22:46:03.559Z",
      "addedCount": 0,
      "changedCount": 0,
      "removedCount": 0,
      "totalFiles": 212,
      "added": [],
      "changed": [],
      "removed": []
    },
    {
      "generatedAt": "2026-02-08T22:37:56.248Z",
      "addedCount": 0,
      "changedCount": 0,
      "removedCount": 0,
      "totalFiles": 212,
      "added": [],
      "changed": [],
      "removed": []
    },
    {
      "generatedAt": "2026-02-08T22:26:28.040Z",
      "addedCount": 0,
      "changedCount": 0,
      "removedCount": 0,
      "totalFiles": 212,
      "added": [],
      "changed": [],
      "removed": []
    },
    {
      "generatedAt": "2026-02-08T22:17:58.198Z",
      "addedCount": 0,
      "changedCount": 0,
      "removedCount": 0,
      "totalFiles": 212,
      "added": [],
      "changed": [],
      "removed": []
    },
    {
      "generatedAt": "2026-02-08T22:10:32.580Z",
      "addedCount": 0,
      "changedCount": 0,
      "removedCount": 0,
      "totalFiles": 212,
      "added": [],
      "changed": [],
      "removed": []
    },
    {
      "generatedAt": "2026-02-08T22:04:01.169Z",
      "addedCount": 0,
      "changedCount": 0,
      "removedCount": 0,
      "totalFiles": 212,
      "added": [],
      "changed": [],
      "removed": []
    },
    {
      "generatedAt": "2026-02-08T22:00:47.777Z",
      "addedCount": 0,
      "changedCount": 0,
      "removedCount": 0,
      "totalFiles": 212,
      "added": [],
      "changed": [],
      "removed": []
    }
  ],
  "latest": {
    "generatedAt": "2026-02-23T06:55:00.613Z",
    "addedCount": 0,
    "changedCount": 1,
    "removedCount": 0,
    "totalFiles": 518
  }
}
